photoarchiver/__init__.py
photoarchiver/__main__.py
photoarchiver/photoarchiver.py
photoarchiver/helpers/__init__.py
photoarchiver/helpers/exif.py
photoarchiver/helpers/file.py
photoarchiver/helpers/path.py
photoarchiver-0.5.dist-info/LICENSE
photoarchiver-0.5.dist-info/METADATA
photoarchiver-0.5.dist-info/WHEEL
photoarchiver-0.5.dist-info/entry_points.txt
photoarchiver-0.5.dist-info/top_level.txt
photoarchiver-0.5.dist-info/RECORD
