Metadata-Version: 2.1
Name: photoarchiver
Version: 0.5
Summary: Archive your photos and files using file timestamps and geolocation.
Home-page: http://github.com/mbaigorria/photoarchiver
Author: Martín Baigorria Alonso
Author-email: martinbaigorria@gmail.com
License: MIT
Platform: UNKNOWN
Classifier: Programming Language :: Python :: 3
Classifier: License :: OSI Approved :: MIT License
Classifier: Operating System :: OS Independent
License-File: LICENSE
Requires-Dist: exifread
Requires-Dist: reverse-geocoder
Requires-Dist: tqdm
Requires-Dist: requests
